netneurotools/__init__.py
netneurotools/_version.py
netneurotools/datasets/__init__.py
netneurotools/datasets/_mirchi2018.py
netneurotools/datasets/datasets.json
netneurotools/datasets/datasets_utils.py
netneurotools/datasets/fetch_atlas.py
netneurotools/datasets/fetch_project.py
netneurotools/datasets/fetch_template.py
netneurotools/datasets/netneurotools.bib
netneurotools/datasets/references.json
netneurotools/datasets/tests/__init__.py
netneurotools/datasets/tests/test_datasets_utils.py
netneurotools/datasets/tests/test_fetch.py
netneurotools/experimental/__init__.py
netneurotools/interface/__init__.py
netneurotools/interface/cifti.py
netneurotools/interface/freesurfer.py
netneurotools/interface/gifti.py
netneurotools/interface/interface_utils.py
netneurotools/interface/surf_parc.py
netneurotools/interface/tests/__init__.py
netneurotools/interface/tests/test_freesurfer.py
netneurotools/interface/tests/test_transforms.py
netneurotools/metrics/__init__.py
netneurotools/metrics/bct.py
netneurotools/metrics/communication.py
netneurotools/metrics/control.py
netneurotools/metrics/metrics_utils.py
netneurotools/metrics/spreading.py
netneurotools/metrics/statistical.py
netneurotools/metrics/tests/__init__.py
netneurotools/metrics/tests/test_bct.py
netneurotools/metrics/tests/test_communication.py
netneurotools/metrics/tests/test_control.py
netneurotools/metrics/tests/test_spreading.py
netneurotools/metrics/tests/test_statistical.py
netneurotools/modularity/__init__.py
netneurotools/modularity/modules.py
netneurotools/modularity/tests/__init__.py
netneurotools/modularity/tests/test_modules.py
netneurotools/networks/__init__.py
netneurotools/networks/consensus.py
netneurotools/networks/generative.py
netneurotools/networks/networks_utils.py
netneurotools/networks/randomize.py
netneurotools/networks/tests/__init__.py
netneurotools/networks/tests/test_consensus.py
netneurotools/networks/tests/test_generative.py
netneurotools/networks/tests/test_networks_utils.py
netneurotools-0.3.0.dist-info/licenses/LICENSE
netneurotools-0.3.0.dist-info/METADATA
netneurotools-0.3.0.dist-info/WHEEL
netneurotools-0.3.0.dist-info/top_level.txt
netneurotools-0.3.0.dist-info/RECORD
