Metadata-Version: 2.4
Name: netneurotools
Version: 0.3.0
Summary: A toolbox for network neuroscience
Author-email: Network Neuroscience Lab <netneurotools-aaaaba25hq3jdluwb2z5h2yr3e@netneurolab.slack.com>
Maintainer-email: Network Neuroscience Lab <netneurotools-aaaaba25hq3jdluwb2z5h2yr3e@netneurolab.slack.com>
License: BSD 3-Clause License
Project-URL: Homepage, https://github.com/netneurolab/netneurotools
Keywords: network neuroscience,connectomics
Classifier: Development Status :: 3 - Alpha
Classifier: Intended Audience :: Science/Research
Classifier: License :: OSI Approved :: BSD License
Classifier: Programming Language :: Python :: 3 :: Only
Requires-Python: >=3.8
License-File: LICENSE
Requires-Dist: bctpy
Requires-Dist: numpy>=1.16
Requires-Dist: scipy>=1.4.0
Requires-Dist: matplotlib
Requires-Dist: scikit-learn
Requires-Dist: nibabel>=3.0.0
Requires-Dist: nilearn
Requires-Dist: tqdm
Provides-Extra: doc
Requires-Dist: sphinx>=2.0; extra == "doc"
Requires-Dist: sphinx_rtd_theme; extra == "doc"
Requires-Dist: sphinx-gallery; extra == "doc"
Provides-Extra: pysurfer
Requires-Dist: vtk; extra == "pysurfer"
Requires-Dist: mayavi; extra == "pysurfer"
Requires-Dist: pysurfer; extra == "pysurfer"
Provides-Extra: pyvista
Requires-Dist: vtk; extra == "pyvista"
Requires-Dist: pyvista; extra == "pyvista"
Provides-Extra: numba
Requires-Dist: numba; extra == "numba"
Provides-Extra: style
Requires-Dist: flake8; extra == "style"
Requires-Dist: ruff; extra == "style"
Provides-Extra: test
Requires-Dist: coverage; extra == "test"
Requires-Dist: pytest>=3.6; extra == "test"
Requires-Dist: pytest-cov; extra == "test"
Dynamic: license-file
